{
    "configurations": [
        {
            "name": "Win32",
            "defines": [
                "_DEBUG",
                "UNICODE",
                "_UNICODE"
            ],
            "intelliSenseMode": "msvc-x64",
            "includePath": [
                "C:/Users/dogan/OneDrive/Documents/Arduino/libraries/**",
                "C:/Users/dogan/OneDrive/Documents/Espressif/**",
                "C:\\Users\\dogan\\AppData\\Local\\Arduino15\\**",
                "${workspaceRoot}/**"
            ]
        }
    ],
    "version": 4
}